LICENSE
MANIFEST.in
README.rst
setup.cfg
setup.py
manhattan/__init__.py
manhattan/client.py
manhattan/middleware.py
manhattan/record.py
manhattan/server.py
manhattan/util.py
manhattan/visitor.py
manhattan/worker.py
manhattan.egg-info/PKG-INFO
manhattan.egg-info/SOURCES.txt
manhattan.egg-info/dependency_links.txt
manhattan.egg-info/entry_points.txt
manhattan.egg-info/not-zip-safe
manhattan.egg-info/requires.txt
manhattan.egg-info/top_level.txt
manhattan/backend/__init__.py
manhattan/backend/cache.py
manhattan/backend/model.py
manhattan/backend/rollups.py
manhattan/backend/persistence/__init__.py
manhattan/backend/persistence/sql.py
manhattan/log/__init__.py
manhattan/log/memory.py
manhattan/log/remote.py
manhattan/log/text.py
manhattan/log/timerotating.py
manhattan/tests/__init__.py
manhattan/tests/base.py
manhattan/tests/data.py
manhattan/tests/test_clientserver.py
manhattan/tests/test_combinations.py
manhattan/tests/test_middleware.py
manhattan/tests/test_remote_log.py
manhattan/tests/test_timerotating_log.py
manhattan/tests/test_util.py