Metadata-Version: 1.1
Name: manhattan
Version: 0.2
Summary: Robust Server-Side Analytics
Home-page: http://github.com/cartlogic/manhattan
Author: Scott Torborg
Author-email: scott@cartlogic.com
License: MIT
Platform: UNKNOWN
Classifier: Development Status :: 5 - Production/Stable
Classifier: Programming Language :: Python :: 2.7
Classifier: Topic :: Internet :: WWW/HTTP :: WSGI :: Middleware
Classifier: Topic :: Internet :: WWW/HTTP :: Site Management
